[{"method_name": "MKL MULTI THREAD", "time": [17.64, 61.52, 828.64, 13275.5, 528905.0]}, {"method_name": "MKL SINGLE THREAD", "time": [15.2, 206.04, 4471.04, 78222.0, 3345050.0]}, {"method_name": "OURS MULTI THREAD", "pre_comp": [3911740.0, 5389210.0, 6588580.0, 15837000.0, 96663500.0], "time": [52.76, 125.92, 346.44, 3348.24, 56821.0]}, {"method_name": "OURS SINGLE THREAD", "time": [3.12, 60.0, 1054.56, 25868.1, 505714.0]}, {"method_name": "EIGEN SINGLE THREAD", "time": [84.52, 1350.2, 28253.0, 557547.0, 12457900.0]}]